rfcontrol/__init__.py
rfcontrol/controller.py
rfcontrol/helpers.py
rfcontrol/py.typed
rfcontrol/protocols/__init__.py
rfcontrol/protocols/_skeleton.py
rfcontrol/protocols/dimmer1.py
rfcontrol/protocols/dimmer2.py
rfcontrol/protocols/generic.py
rfcontrol/protocols/generic2.py
rfcontrol/protocols/pir1.py
rfcontrol/protocols/pir2.py
rfcontrol/protocols/pir3.py
rfcontrol/protocols/pir4.py
rfcontrol/protocols/pir6.py
rfcontrol/protocols/switch1.py
rfcontrol/protocols/switch10.py
rfcontrol/protocols/switch11.py
rfcontrol/protocols/switch2.py
rfcontrol/protocols/switch25.py
rfcontrol/protocols/switch3.py
rfcontrol/protocols/switch4.py
rfcontrol/protocols/switch5.py
rfcontrol/protocols/switch6.py
rfcontrol/protocols/switch7.py
rfcontrol/protocols/switch8.py
rfcontrol/protocols/weather13.py
rfcontrol/protocols/weather19.py
rfcontrol/protocols/weather4.py
rfcontrol/protocols/weather7.py
rfcontrolpy-0.0.10.dist-info/licenses/LICENSE
rfcontrolpy-0.0.10.dist-info/METADATA
rfcontrolpy-0.0.10.dist-info/WHEEL
rfcontrolpy-0.0.10.dist-info/top_level.txt
rfcontrolpy-0.0.10.dist-info/RECORD
