Metadata-Version: 2.4
Name: rfcontrolpy
Version: 0.0.10
Summary: Library with protocol support for different 433MHz switches and weather stations for the RFControl Arduino library.
Author-email: Rogier van Staveren <rogier@batoid.com>
License: GPLv3
Project-URL: Homepage, https://github.com/rrooggiieerr/rfcontrolpy
Project-URL: Issues, https://github.com/rrooggiieerr/rfcontrolpy/issues
Classifier: Development Status :: 4 - Beta
Classifier: Intended Audience :: Developers
Classifier: License :: OSI Approved :: GNU General Public License v3 (GPLv3)
Classifier: Operating System :: MacOS :: MacOS X
Classifier: Operating System :: POSIX
Classifier: Programming Language :: Python :: 3.11
Classifier: Programming Language :: Python :: 3.12
Classifier: Topic :: Home Automation
Classifier: Topic :: Software Development :: Libraries :: Python Modules
Requires-Python: >=3.11
License-File: LICENSE
Dynamic: license-file
